k8kat/__init__.py
k8kat/broker.py
k8kat/types.py
k8kat/e2e_tests/__init__.py
k8kat/e2e_tests/test_broker.py
k8kat/e2e_tests/test_configmap.py
k8kat/e2e_tests/test_ingress.py
k8kat/e2e_tests/test_pod.py
k8kat/e2e_tests/test_secret.py
k8kat/e2e_tests/test_service_account.py
k8kat/res/__init__.py
k8kat/res/base_resource.py
k8kat/res/configmap.py
k8kat/res/ingress.py
k8kat/res/pod.py
k8kat/res/pod_utils.py
k8kat/res/secret.py
k8kat/res/selectors.py
k8kat/res/service_account.py
k8kat/utils/__init__.py
k8kat/utils/class_property.py
k8kat/utils/units.py
k8kat-0.1.2.dist-info/METADATA
k8kat-0.1.2.dist-info/WHEEL
k8kat-0.1.2.dist-info/top_level.txt
k8kat-0.1.2.dist-info/RECORD
