Metadata-Version: 2.1
Name: k8kat
Version: 0.1.2
Summary: Sugar for Kubernetes
Home-page: https://github.com/nmachine-cs/k8kat
Author: NMachine
Author-email: xavier@nmachine.io
License: UNKNOWN
Platform: UNKNOWN
Classifier: Programming Language :: Python :: 3
Classifier: License :: OSI Approved :: MIT License
Classifier: Operating System :: OS Independent
Requires-Python: >=3.6
Requires-Dist: inflection
Requires-Dist: kubernetes
Requires-Dist: python-dotenv
Requires-Dist: typing-extensions
